Xana/Analist.py
Xana/Analysis.py
Xana/Decorators.py
Xana/Setup.py
Xana/Xana.py
Xana/Xdb.py
Xana/__init__.py
Xana/helper.py
Xana/ProcData/ArrangeModules.py
Xana/ProcData/CbfMethods.py
Xana/ProcData/EdfFile3.py
Xana/ProcData/EdfMethods.py
Xana/ProcData/H5Methods.py
Xana/ProcData/NxsMethods.py
Xana/ProcData/ReadData.py
Xana/ProcData/Xdata.py
Xana/ProcData/Xfmt.py
Xana/ProcData/__init__.py
Xana/ProcData/getmeta.py
Xana/ProcData/to_h5.py
Xana/SaxsAna/Saxs.py
Xana/SaxsAna/Soq.py
Xana/SaxsAna/__init__.py
Xana/SaxsAna/defineqrois.py
Xana/SaxsAna/find_center.py
Xana/SaxsAna/integrate.py
Xana/SaxsAna/phicorr.py
Xana/SaxsAna/pysaxs3.py
Xana/XParam/__init__.py
Xana/XParam/parameters.py
Xana/XParam/scratch.py
Xana/Xdrop/DropletizeData.py
Xana/Xdrop/__init__.py
Xana/Xfit/BandyFunctions.py
Xana/Xfit/DetectorCorrection.py
Xana/Xfit/DetectorCorrection2.py
Xana/Xfit/FitPoissonGamma.py
Xana/Xfit/FitPoissonGammaLikelihood.py
Xana/Xfit/MCMC_straight_line.py
Xana/Xfit/PlotPoissonGamma.py
Xana/Xfit/PoissonGammaDistribution.py
Xana/Xfit/SelectData.py
Xana/Xfit/__init__.py
Xana/Xfit/basic.py
Xana/Xfit/fitBandy.orig.py
Xana/Xfit/fitBandy.py
Xana/Xfit/fit_basic.py
Xana/Xfit/fitg2.py
Xana/Xfit/fitg2global.py
Xana/Xfit/fitgaussian.py
Xana/Xfit/relaxationfunctions.py
Xana/XpcsAna/CorrFunc.py
Xana/XpcsAna/StaticContrast.py
Xana/XpcsAna/Xpcs.py
Xana/XpcsAna/__init__.py
Xana/XpcsAna/cpy_ecorr.cpython-37m-darwin.so
Xana/XpcsAna/eventcorrelator3.py
Xana/XpcsAna/map2ct.py
Xana/XpcsAna/mp_corr3_err.py
Xana/XpcsAna/pyxpcs3.py
Xana/XpcsAna/radialprofile.py
Xana/XpcsAna/xpcsmethods.py
Xana/Xplot/PlotPoissonGamma.py
Xana/Xplot/__init__.py
Xana/Xplot/niceplot.py
Xana/Xplot/plot1img.py
Xana/Xplot/plot1imgEDF.py
Xana/Xplot/plotqrois.py
Xana/XsvsAna/CheckPoissonGamma.py
Xana/XsvsAna/PhotonStats.py
Xana/XsvsAna/PlotContrast.py
Xana/XsvsAna/ProbSum.py
Xana/XsvsAna/VisbFunc.py
Xana/XsvsAna/Xsvs.py
Xana/XsvsAna/__init__.py
Xana/XsvsAna/analyze.py
Xana/XsvsAna/betaratio.py
Xana/XsvsAna/mp_prob.py
Xana-0.7.4.dist-info/LICENSE
Xana-0.7.4.dist-info/METADATA
Xana-0.7.4.dist-info/WHEEL
Xana-0.7.4.dist-info/top_level.txt
Xana-0.7.4.dist-info/RECORD
