Metadata-Version: 2.1
Name: Xana
Version: 0.7.4
Summary: Analysis software for XPCS, XSVS and SAXS data.
Home-page: https://github.com/reiserm/Xana
Author: Mario Reiser
Author-email: mario.mkel@gmail.com
License: MIT
Download-URL: https://github.com/reiserm/Xana/archive/v0.7.4.tar.gz
Keywords: data analysis,XPCS,XSVS,SAXS
Platform: UNKNOWN
Classifier: Development Status :: 3 - Alpha
Classifier: Intended Audience :: Science/Research
Classifier: Topic :: Scientific/Engineering :: Physics
Classifier: License :: OSI Approved :: MIT License
Classifier: Programming Language :: Python :: 3
Classifier: Programming Language :: Python :: 3.6
Classifier: Programming Language :: Python :: 3.7
Requires-Python: >= 3.6
License-File: LICENSE
Requires-Dist: corner (>=2.0)
Requires-Dist: emcee (>=3.0)
Requires-Dist: h5py (>=2.0)
Requires-Dist: hdf5plugin
Requires-Dist: ipywidgets
Requires-Dist: lmfit (>=1.0)
Requires-Dist: matplotlib
Requires-Dist: numpy (>=1.19)
Requires-Dist: pandas (>=1.0)
Requires-Dist: pyfai (>=0.19)
Requires-Dist: seaborn
Requires-Dist: cython
Provides-Extra: test
Requires-Dist: pytest ; extra == 'test'
Requires-Dist: pytest-cov ; extra == 'test'
Requires-Dist: nbval ; extra == 'test'
